qw_map/__init__.py
qw_map/index.py
qW_Map-0.1.2.dist-info/LICENSE
qW_Map-0.1.2.dist-info/METADATA
qW_Map-0.1.2.dist-info/WHEEL
qW_Map-0.1.2.dist-info/top_level.txt
qW_Map-0.1.2.dist-info/RECORD
