Metadata-Version: 2.1
Name: qW-Map
Version: 0.1.2
Summary: A PyTorch implementation of Quantum Weight Re-Mapping
Home-page: https://github.com/michaelkoelle/quantum-weight-remapping
Author: Michael Kölle
Author-email: michael.koelle@ifi.lmu.de
License: MIT
Keywords: quantum artificial intelligence,pytorch,quantum machine learning,weight re-mapping,quantum supervised learning,quantum variational circuit,quantum variational classifier,pennylane
Classifier: Development Status :: 4 - Beta
Classifier: Intended Audience :: Developers
Classifier: Topic :: Scientific/Engineering :: Artificial Intelligence
Classifier: License :: OSI Approved :: MIT License
Classifier: Programming Language :: Python :: 3.6
License-File: LICENSE
Requires-Dist: torch (>=1.6)
